{"version": 0.6, "generator": "Overpass API 0.7.62.11 87bfad18", "osm3s": {"timestamp_osm_base": "2026-04-30T15:33:12Z", "copyright": "The data included in this document is from www.openstreetmap.org. The data is made available under ODbL."}, "elements": [{"type": "node", "id": 2360535649, "lat": 52.7470385, "lon": 15.1465928}, {"type": "node", "id": 2360535654, "lat": 52.7471425, "lon": 15.1461101}, {"type": "node", "id": 7830167139, "lat": 52.7472811, "lon": 15.1467317}, {"type": "node", "id": 7830167143, "lat": 52.7472963, "lon": 15.1466611}, {"type": "node", "id": 7830167144, "lat": 52.7473274, "lon": 15.1466796}, {"type": "node", "id": 7830167145, "lat": 52.7473122, "lon": 15.1467498}, {"type": "node", "id": 7830167148, "lat": 52.7470557, "lon": 15.1465181}, {"type": "node", "id": 7830167149, "lat": 52.7469565, "lon": 15.1464566}, {"type": "node", "id": 7830167150, "lat": 52.7469389, "lon": 15.1465341}, {"type": "node", "id": 7830167151, "lat": 52.7471079, "lon": 15.1460904}, {"type": "node", "id": 7830167152, "lat": 52.7470927, "lon": 15.1461635}, {"type": "node", "id": 7830167153, "lat": 52.7471273, "lon": 15.1461831}, {"type": "node", "id": 7938971541, "lat": 52.7418702, "lon": 15.1554178}, {"type": "node", "id": 7938971542, "lat": 52.7418487, "lon": 15.1554055}, {"type": "node", "id": 7938971544, "lat": 52.7418857, "lon": 15.1553436}, {"type": "node", "id": 7938971545, "lat": 52.7418642, "lon": 15.1553314}, {"type": "node", "id": 7938971548, "lat": 52.7419072, "lon": 15.1553558}, {"type": "node", "id": 7938971549, "lat": 52.7418917, "lon": 15.15543}, {"type": "node", "id": 7944401599, "lat": 52.7335619, "lon": 15.1546131}, {"type": "node", "id": 7944401606, "lat": 52.7335381, "lon": 15.1546734}, {"type": "node", "id": 7944401607, "lat": 52.7335619, "lon": 15.154699}, {"type": "node", "id": 7944401608, "lat": 52.7335857, "lon": 15.1546387}, {"type": "node", "id": 7947743138, "lat": 52.7472898, "lon": 15.1394186}, {"type": "node", "id": 7947743167, "lat": 52.7472868, "lon": 15.1394736}, {"type": "node", "id": 7947743168, "lat": 52.7473303, "lon": 15.13948}, {"type": "node", "id": 7947743174, "lat": 52.7473332, "lon": 15.139425}, {"type": "node", "id": 8325417596, "lat": 52.7765859, "lon": 14.9474094}, {"type": "node", "id": 8325417597, "lat": 52.7765868, "lon": 14.9473292}, {"type": "node", "id": 8325417598, "lat": 52.776553, "lon": 14.9473297}, {"type": "node", "id": 8325417599, "lat": 52.7765527, "lon": 14.9474083}, {"type": "node", "id": 9161055645, "lat": 52.7405211, "lon": 15.1430564}, {"type": "node", "id": 9161055646, "lat": 52.7405523, "lon": 15.143075}, {"type": "node", "id": 9161055647, "lat": 52.7405357, "lon": 15.1429893}, {"type": "node", "id": 9161055648, "lat": 52.7405669, "lon": 15.1430079}, {"type": "node", "id": 9161055649, "lat": 52.7405051, "lon": 15.1429712}, {"type": "node", "id": 9161055651, "lat": 52.7405981, "lon": 15.1430264}, {"type": "node", "id": 9161055652, "lat": 52.7405835, "lon": 15.1430935}, {"type": "node", "id": 9161055664, "lat": 52.7404905, "lon": 15.1430383}, {"type": "node", "id": 9161065125, "lat": 52.7405336, "lon": 15.1430639}, {"type": "node", "id": 9161135120, "lat": 52.7508151, "lon": 15.1300355}, {"type": "node", "id": 9161135121, "lat": 52.7507963, "lon": 15.1301022}, {"type": "node", "id": 9161135122, "lat": 52.7507669, "lon": 15.1300795}, {"type": "node", "id": 9161135134, "lat": 52.7508256, "lon": 15.1301249}, {"type": "node", "id": 9161135135, "lat": 52.7508445, "lon": 15.1300582}, {"type": "node", "id": 9161135169, "lat": 52.7507858, "lon": 15.1300128}, {"type": "node", "id": 9161247687, "lat": 52.7496992, "lon": 15.1291704}, {"type": "node", "id": 9161247688, "lat": 52.7497109, "lon": 15.1290981}, {"type": "node", "id": 9161247689, "lat": 52.7496664, "lon": 15.1291558}, {"type": "node", "id": 9161247690, "lat": 52.7496782, "lon": 15.1290836}, {"type": "way", "id": 839085123, "nodes": [7830167143, 7830167144, 7830167145, 7830167139, 7830167143], "tags": {"amenity": "parking_space", "capacity": "1", "parking_space": "disabled"}}, {"type": "way", "id": 839085125, "nodes": [7830167148, 7830167149, 7830167150, 2360535649, 7830167148], "tags": {"amenity": "parking_space", "capacity": "3", "parking_space": "disabled"}}, {"type": "way", "id": 839085126, "nodes": [7830167151, 7830167152, 7830167153, 2360535654, 7830167151], "tags": {"amenity": "parking_space", "capacity": "1", "parking_space": "disabled"}}, {"type": "way", "id": 851112652, "nodes": [7938971544, 7938971548, 7938971549, 7938971541, 7938971544], "tags": {"amenity": "parking_space", "parking_space": "disabled", "wheelchair": "designated"}}, {"type": "way", "id": 851112653, "nodes": [7938971545, 7938971544, 7938971541, 7938971542, 7938971545], "tags": {"amenity": "parking_space", "parking_space": "disabled", "wheelchair": "designated"}}, {"type": "way", "id": 851762118, "nodes": [7944401607, 7944401606, 7944401599, 7944401608, 7944401607], "tags": {"amenity": "parking_space", "capacity": "1", "parking_space": "disabled"}}, {"type": "way", "id": 852037498, "nodes": [7947743167, 7947743138, 7947743174, 7947743168, 7947743167], "tags": {"amenity": "parking_space", "parking_space": "disabled", "wheelchair": "designated"}}, {"type": "way", "id": 895653242, "nodes": [8325417596, 8325417597, 8325417598, 8325417599, 8325417596], "tags": {"amenity": "parking_space", "capacity": "1", "parking_space": "disabled"}}, {"type": "way", "id": 991536990, "nodes": [9161055647, 9161055645, 9161055664, 9161055649, 9161055647], "tags": {"amenity": "parking_space", "capacity": "1", "capacity:disabled": "1", "parking_space": "disabled"}}, {"type": "way", "id": 991536991, "nodes": [9161055648, 9161055646, 9161065125, 9161055645, 9161055647, 9161055648], "tags": {"amenity": "parking_space", "capacity": "1", "capacity:disabled": "1", "parking_space": "disabled"}}, {"type": "way", "id": 991536992, "nodes": [9161055651, 9161055652, 9161055646, 9161055648, 9161055651], "tags": {"amenity": "parking_space", "capacity": "1", "capacity:disabled": "1", "parking_space": "disabled"}}, {"type": "way", "id": 991543574, "nodes": [9161135121, 9161135122, 9161135169, 9161135120, 9161135121], "tags": {"amenity": "parking_space", "capacity": "1", "capacity:disabled": "1", "parking_space": "disabled"}}, {"type": "way", "id": 991543575, "nodes": [9161135134, 9161135121, 9161135120, 9161135135, 9161135134], "tags": {"amenity": "parking_space", "capacity": "1", "capacity:disabled": "1", "parking_space": "disabled"}}, {"type": "way", "id": 991555438, "nodes": [9161247688, 9161247690, 9161247689, 9161247687, 9161247688], "tags": {"amenity": "parking_space", "capacity": "1", "capacity:disabled": "1", "parking_space": "disabled"}}]}